folder_merger/__init__.py
folder_merger/cli.py
folder_merger/merger.py
folder_merger-0.1.0.dist-info/licenses/LICENSE
folder_merger-0.1.0.dist-info/METADATA
folder_merger-0.1.0.dist-info/WHEEL
folder_merger-0.1.0.dist-info/entry_points.txt
folder_merger-0.1.0.dist-info/top_level.txt
folder_merger-0.1.0.dist-info/RECORD
